CHANGES.txt
COPYRIGHT.txt
LICENSE.txt
MANIFEST.in
README-shorttests.txt
README.txt
setup.py
tests.txt
datashackleproject/__init__.py
datashackleproject/main.py
datashackleproject/templates.py
datashackleproject/utils.py
datashackleproject.egg-info/PKG-INFO
datashackleproject.egg-info/SOURCES.txt
datashackleproject.egg-info/dependency_links.txt
datashackleproject.egg-info/entry_points.txt
datashackleproject.egg-info/not-zip-safe
datashackleproject.egg-info/requires.txt
datashackleproject.egg-info/top_level.txt
datashackleproject/template/bootstrap.py
datashackleproject/template/buildout.cfg_tmpl
datashackleproject/template/bin/pidproxy.py
datashackleproject/template/etc/debug.ini.in_tmpl
datashackleproject/template/etc/deploy.ini.in_tmpl
datashackleproject/template/etc/production.ini.in
datashackleproject/template/etc/pyramid_development.ini.in_tmpl
datashackleproject/template/etc/pyramid_production.ini.in_tmpl
datashackleproject/template/etc/site.zcml.in_tmpl
datashackleproject/template/etc/zope.conf.in_tmpl
datashackleproject/template/profiles/datashackle.cfg_tmpl
datashackleproject/template/profiles/defaults.cfg_tmpl
datashackleproject/template/profiles/versions.cfg
datashackleproject/template/src/grok/+package+/setup.py_tmpl
datashackleproject/template/src/grok/+package+/+package+/README.txt
datashackleproject/template/src/grok/+package+/+package+/__init__.py
datashackleproject/template/src/grok/+package+/+package+/application.py_tmpl
datashackleproject/template/src/grok/+package+/+package+/configure.zcml
datashackleproject/template/src/grok/+package+/+package+/ftesting.zcml
datashackleproject/template/src/grok/+package+/+package+/interfaces.py_tmpl
datashackleproject/template/src/grok/+package+/+package+/resource.py_tmpl
datashackleproject/template/src/grok/+package+/+package+/static/README.txt
datashackleproject/template/src/grok/+package+/+package+/static/style.css
datashackleproject/template/src/grok/+package+/+package+/tests/__init__.py
datashackleproject/template/src/grok/+package+/+package+/tests/app.txt_tmpl
datashackleproject/template/src/grok/+package+/+package+/tests/ftesting.zcml_tmpl
datashackleproject/template/src/grok/+package+/+package+/tests/test_+project_lowercase+.py_tmpl
