Metadata-Version: 1.0
Name: datashackleproject
Version: 0.1.6
Summary: Script that creates a Datashackle skeleton for a new Datashackle web application.
Home-page: http://datashackle.net
Author: Michael Jenny
Author-email: michaelj@datashackle.net
License: GPL
Platform: UNKNOWN
